LICENSE
MANIFEST.in
README.rst
setup.py
contacts/__init__.py
contacts/admin.py
contacts/forms.py
contacts/models.py
contacts/urls.py
contacts/views.py
django_simple_contacts.egg-info/PKG-INFO
django_simple_contacts.egg-info/SOURCES.txt
django_simple_contacts.egg-info/dependency_links.txt
django_simple_contacts.egg-info/pbr.json
django_simple_contacts.egg-info/top_level.txt