Metadata-Version: 1.1
Name: django-simple-contacts
Version: 0.1
Summary: A Django app for creating and managing simple set of contacts
Home-page: https://github.com/renkse/django-simple-contacts
Author: renkse
Author-email: solomon_art@mail.ru
License: BSD License
Download-URL: https://github.com/renkse/django-simple-contacts/tarball/0.1
Platform: UNKNOWN
Classifier: Development Status :: 4 - Beta
Classifier: Environment :: Web Environment
Classifier: Framework :: Django
Classifier: Intended Audience :: Developers
Classifier: License :: OSI Approved :: BSD License
Classifier: Operating System :: OS Independent
Classifier: Programming Language :: Python
Classifier: Programming Language :: Python :: 2.6
Classifier: Programming Language :: Python :: 2.7
Classifier: Topic :: Internet :: WWW/HTTP
Classifier: Topic :: Internet :: WWW/HTTP :: Dynamic Content
